ychaos-0.5.781648-py3.7-nspkg.pth
ychaos/app_logger.py
ychaos/settings.py
ychaos/agents/__init__.py
ychaos/agents/agent.py
ychaos/agents/contrib.py
ychaos/agents/coordinator.py
ychaos/agents/index.py
ychaos/agents/exceptions/__init__.py
ychaos/agents/network/__init__.py
ychaos/agents/network/iptables.py
ychaos/agents/network/traffic.py
ychaos/agents/special/NoOpAgent.py
ychaos/agents/special/__init__.py
ychaos/agents/system/__init__.py
ychaos/agents/system/cpu.py
ychaos/agents/system/disk.py
ychaos/agents/system/icmp.py
ychaos/agents/system/shell.py
ychaos/agents/utils/__init__.py
ychaos/agents/utils/annotations.py
ychaos/agents/utils/sysctl.py
ychaos/agents/validation/__init__.py
ychaos/agents/validation/certificate.py
ychaos/cli/__init__.py
ychaos/cli/execute.py
ychaos/cli/main.py
ychaos/cli/manual.py
ychaos/cli/mock.py
ychaos/cli/verify.py
ychaos/cli/agent/__init__.py
ychaos/cli/agent/attack.py
ychaos/cli/agent/main.py
ychaos/cli/exceptions/__init__.py
ychaos/cli/testplan/__init__.py
ychaos/cli/testplan/main.py
ychaos/cli/testplan/validate.py
ychaos/core/__init__.py
ychaos/core/exceptions/__init__.py
ychaos/core/exceptions/executor_errors.py
ychaos/core/executor/BaseExecutor.py
ychaos/core/executor/MachineTargetExecutor.py
ychaos/core/executor/SelfTargetExecutor.py
ychaos/core/executor/__init__.py
ychaos/core/executor/common.py
ychaos/core/verification/__init__.py
ychaos/core/verification/controller.py
ychaos/core/verification/data.py
ychaos/core/verification/plugins/BaseVerificationPlugin.py
ychaos/core/verification/plugins/HTTPRequestVerificationPlugin.py
ychaos/core/verification/plugins/OpenTSDBVerificationPlugin.py
ychaos/core/verification/plugins/PythonModuleVerificationPlugin.py
ychaos/core/verification/plugins/SDv4VerificationPlugin.py
ychaos/core/verification/plugins/__init__.py
ychaos/testplan/__init__.py
ychaos/testplan/attack.py
ychaos/testplan/common.py
ychaos/testplan/schema.py
ychaos/testplan/validator.py
ychaos/testplan/resources/__init__.py
ychaos-0.5.781648.dist-info/LICENSE
ychaos-0.5.781648.dist-info/METADATA
ychaos-0.5.781648.dist-info/WHEEL
ychaos-0.5.781648.dist-info/entry_points.txt
ychaos-0.5.781648.dist-info/namespace_packages.txt
ychaos-0.5.781648.dist-info/top_level.txt
ychaos-0.5.781648.dist-info/RECORD
