Metadata-Version: 2.1
Name: ychaos
Version: 0.5.781648
Summary: Python module ychaos
Home-page: https://github.com/yahoo/ychaos
Author: Resilience Team
Author-email: ychaos-dev@yahooinc.com
License: UNKNOWN
Project-URL: Documentation, https://yahoo.github.io/ychaos
Project-URL: Source, https://github.com/yahoo/ychaos
Project-URL: Changelog, https://yahoo.github.io/ychaos/releases/
Project-URL: CI Pipeline, https://cd.screwdriver.cd/pipelines/7419
Project-URL: Download, https://pypi.org/project/ychaos/#files
Keywords: ychaos,testing,resilience,chaos,engineering
Platform: UNKNOWN
Classifier: Development Status :: 5 - Production/Stable
Classifier: License :: OSI Approved :: Apache Software License
Classifier: Programming Language :: Python :: 3 :: Only
Classifier: Programming Language :: Python :: 3.7
Classifier: Programming Language :: Python :: 3.8
Classifier: Programming Language :: Python :: 3.9
Classifier: Natural Language :: English
Classifier: Operating System :: POSIX :: Linux
Classifier: Topic :: Security
Classifier: Topic :: Scientific/Engineering
Classifier: Topic :: System :: Benchmark
Requires-Python: >="3.7"
License-File: LICENSE
Requires-Dist: pydantic (==1.9.0)
Requires-Dist: pyyaml (==6.0)
Requires-Dist: requests (==2.27.1)
Requires-Dist: rich (==12.0.1)
Provides-Extra: agents
Requires-Dist: psutil (==5.9.0) ; extra == 'agents'
Requires-Dist: pyOpenSSL (==22.0.0) ; extra == 'agents'
Provides-Extra: all
Requires-Dist: ansible (==3.2.0) ; extra == 'all'
Requires-Dist: psutil (==5.9.0) ; extra == 'all'
Requires-Dist: pyOpenSSL (==22.0.0) ; extra == 'all'
Provides-Extra: chaos
Requires-Dist: ansible (==3.2.0) ; extra == 'chaos'
Provides-Extra: debug
Requires-Dist: mkdocs ; extra == 'debug'
Requires-Dist: mkdocs-material (>=7.0.0) ; extra == 'debug'
Requires-Dist: mkdocstrings ; extra == 'debug'
Requires-Dist: mkdocs-awesome-pages-plugin ; extra == 'debug'
Requires-Dist: json-schema-for-humans ; extra == 'debug'
Requires-Dist: markdown-include ; extra == 'debug'
Requires-Dist: flake8 ; extra == 'debug'
Requires-Dist: bandit ; extra == 'debug'
Requires-Dist: pre-commit ; extra == 'debug'
Requires-Dist: codespell ; extra == 'debug'
Requires-Dist: mypy ; extra == 'debug'
Requires-Dist: types-PyYAML ; extra == 'debug'
Requires-Dist: types-requests ; extra == 'debug'
Requires-Dist: types-setuptools ; extra == 'debug'
Requires-Dist: pytest ; extra == 'debug'
Requires-Dist: pytest-cov ; extra == 'debug'
Requires-Dist: pytest-timeout ; extra == 'debug'
Requires-Dist: pytest-xdist ; extra == 'debug'
Requires-Dist: mockito ; extra == 'debug'
Requires-Dist: callee ; extra == 'debug'
Requires-Dist: parameterized ; extra == 'debug'
Requires-Dist: jsondiff ; extra == 'debug'
Requires-Dist: coverage (<6.0) ; extra == 'debug'
Requires-Dist: isort ; extra == 'debug'
Requires-Dist: black ; extra == 'debug'
Requires-Dist: absolufy-imports ; extra == 'debug'
Requires-Dist: ansible (==3.2.0) ; extra == 'debug'
Requires-Dist: psutil (==5.9.0) ; extra == 'debug'
Requires-Dist: pyOpenSSL (==22.0.0) ; extra == 'debug'
Provides-Extra: doc_build
Requires-Dist: mkdocs ; extra == 'doc_build'
Requires-Dist: mkdocs-material (>=7.0.0) ; extra == 'doc_build'
Requires-Dist: mkdocstrings ; extra == 'doc_build'
Requires-Dist: mkdocs-awesome-pages-plugin ; extra == 'doc_build'
Requires-Dist: markdown-include ; extra == 'doc_build'
Requires-Dist: json-schema-for-humans ; extra == 'doc_build'
Requires-Dist: psutil (==5.9.0) ; extra == 'doc_build'
Requires-Dist: pyOpenSSL (==22.0.0) ; extra == 'doc_build'
Requires-Dist: livereload ; extra == 'doc_build'
Provides-Extra: mypy
Requires-Dist: mypy ; extra == 'mypy'
Requires-Dist: types-PyYAML ; extra == 'mypy'
Requires-Dist: types-requests ; extra == 'mypy'
Requires-Dist: types-setuptools ; extra == 'mypy'
Provides-Extra: pep8
Requires-Dist: black ; extra == 'pep8'
Requires-Dist: flake8 ; extra == 'pep8'
Requires-Dist: codespell ; extra == 'pep8'
Provides-Extra: pylint
Provides-Extra: test
Requires-Dist: mockito ; extra == 'test'
Requires-Dist: jsondiff ; extra == 'test'
Requires-Dist: coverage (<6.0) ; extra == 'test'
Requires-Dist: cryptography ; extra == 'test'
Requires-Dist: ansible (==3.2.0) ; extra == 'test'
Requires-Dist: psutil (==5.9.0) ; extra == 'test'
Requires-Dist: pyOpenSSL (==22.0.0) ; extra == 'test'
Requires-Dist: pytest-timeout ; extra == 'test'
Requires-Dist: parameterized ; extra == 'test'
